pytacs/__init__.py
pytacs/classifier.py
pytacs/data.py
pytacs/plot.py
pytacs/spatial.py
pytacs/spatial_deprecated.py
pytacs/types.py
pytacs/utils.py
pytacs-2025.9.15.dist-info/LICENSE
pytacs-2025.9.15.dist-info/METADATA
pytacs-2025.9.15.dist-info/WHEEL
pytacs-2025.9.15.dist-info/RECORD
