Metadata-Version: 2.3
Name: pytacs
Version: 2025.9.15
Summary: Pytacs: Python-implemented Topology-Aware Cell Segmentation for high-resolution spatial transcriptomics
License: GPL3
Author: Xindong Liu
Author-email: lqxnds@foxmail.com
Requires-Python: >=3.12
Classifier: License :: Other/Proprietary License
Classifier: Programming Language :: Python :: 3
Classifier: Programming Language :: Python :: 3.12
Classifier: Programming Language :: Python :: 3.13
Requires-Dist: dill (>=0.3.8,<0.4.0)
Requires-Dist: matplotlib (>=3.9.2,<3.10.0)
Requires-Dist: numpy (>=1.26.4,<1.27.0)
Requires-Dist: pandas (>=2.2.3,<2.3.0)
Requires-Dist: scanpy (>=1.10.4,<1.11.0)
Requires-Dist: scikit-learn (>=1.5.2,<1.6.0)
Requires-Dist: scipy (>=1.14.1,<1.15.0)
Requires-Dist: seaborn (>=0.13.2,<0.14.0)
